[
  {
    "name": "Abdullah Ibrahim",
    "username": "aibrahim"
  },
  {
    "name": "Andres Ramos",
    "username": "aramos"
  },
  {
    "name": "Annika Rangarajan",
    "username": "arangarajan"
  },
  {
    "name": "Crystal Wu",
    "username": "cwu"
  },
  {
    "name": "Donald Stephens",
    "username": "dstephens"
  },
  {
    "name": "Eva Lien",
    "username": "elien"
  },
  {
    "name": "Grace Harris",
    "username": "gharris"
  },
  {
    "name": "Hassana Ajayi",
    "username": "hajayi"
  },
  {
    "name": "Joshua Williams",
    "username": "jwilliams"
  },
  {
    "name": "Molly Clark",
    "username": "mclark"
  },
  {
    "name": "Phan Kim",
    "username": "pkim"
  },
  {
    "name": "Samuel Hall",
    "username": "shall"
  },
  {
    "name": "Stefanie Auer",
    "username": "sauer"
  },
  {
    "name": "Taha Kandemir",
    "username": "tkandemir"
  },
  {
    "name": "Zlatica Chalupka",
    "username": "zchalupka"
  }
]
